{"skeleton":{"hash":"4bQ0KKU5rEcc+M+LDXPZOHKzhcQ","spine":"2.1.27","width":123.46,"height":123.46,"images":""},"bones":[{"name":"root"},{"name":"bone16","parent":"root","x":-35.72,"y":68.26,"scaleX":1.646,"scaleY":1.646}],"slots":[{"name":"1231243","bone":"bone16","attachment":"dhjs_buff_a_00014","blend":"additive"}],"skins":{"default":{"1231243":{"dhjs_buff_a_00000":{"width":75,"height":75},"dhjs_buff_a_00002":{"width":75,"height":75},"dhjs_buff_a_00004":{"width":75,"height":75},"dhjs_buff_a_00006":{"width":75,"height":75},"dhjs_buff_a_00008":{"width":75,"height":75},"dhjs_buff_a_00010":{"width":75,"height":75},"dhjs_buff_a_00012":{"width":75,"height":75},"dhjs_buff_a_00014":{"width":75,"height":75},"dhjs_buff_a_00016":{"width":75,"height":75}}}},"animations":{"idle":{"slots":{"1231243":{"attachment":[{"time":0,"name":"dhjs_buff_a_00000"},{"time":0.0666,"name":"dhjs_buff_a_00002"},{"time":0.1333,"name":"dhjs_buff_a_00004"},{"time":0.2,"name":"dhjs_buff_a_00006"},{"time":0.2666,"name":"dhjs_buff_a_00008"},{"time":0.3333,"name":"dhjs_buff_a_00010"},{"time":0.4,"name":"dhjs_buff_a_00012"},{"time":0.4666,"name":"dhjs_buff_a_00014"},{"time":0.5333,"name":"dhjs_buff_a_00016"}]}},"bones":{"bone16":{"translate":[{"time":0,"x":35.19,"y":-67.72}],"scale":[{"time":0,"x":1.112,"y":1}]}}}}}