{"skeleton":{"hash":"HAUSN//fV1f7XArzBTu6qy7Xgoo","spine":"2.1.27","width":111,"height":56,"images":""},"bones":[{"name":"root"},{"name":"bone","parent":"root","x":-1.49,"y":-1.76}],"slots":[{"name":"hat_fd01","bone":"bone","attachment":"hat_fd03"}],"skins":{"default":{"hat_fd01":{"hat_fd01":{"width":111,"height":56},"hat_fd02":{"width":111,"height":56},"hat_fd03":{"width":111,"height":56}}}},"animations":{"idle":{"slots":{"hat_fd01":{"attachment":[{"time":0,"name":"hat_fd01"},{"time":0.0666,"name":"hat_fd02"},{"time":0.1333,"name":"hat_fd03"},{"time":0.2,"name":"hat_fd01"}]}},"bones":{"bone":{"rotate":[{"time":0,"angle":0,"curve":"stepped"},{"time":0.1333,"angle":0}],"translate":[{"time":0,"x":0,"y":0,"curve":"stepped"},{"time":0.1333,"x":0,"y":0}],"scale":[{"time":0,"x":1,"y":1,"curve":"stepped"},{"time":0.1333,"x":1,"y":1}]},"root":{"scale":[{"time":0,"x":0.8,"y":0.8}]}},"drawOrder":[{"time":0.0666}]}}}